[
  {
    "date": "2021-06-01",
    "profit": 31102,
    "stores": 850
  },
  {
    "date": "2021-07-01",
    "profit": 31102,
    "stores": 850
  },
  {
    "date": "2021-08-01",
    "profit": 31102,
    "stores": 850
  },
  {
    "date": "2021-09-01",
    "profit": 63924,
    "stores": 810
  },
  {
    "date": "2021-10-01",
    "profit": 38144,
    "stores": 343
  },
  {
    "date": "2021-11-01",
    "profit": 43991,
    "stores": 537
  },
  {
    "date": "2021-12-01",
    "profit": 43781,
    "stores": 386
  },
  {
    "date": "2022-01-01",
    "profit": 46242,
    "stores": 301
  },
  {
    "date": "2022-02-01",
    "profit": 73986,
    "stores": 193
  },
  {
    "date": "2022-03-01",
    "profit": 86522,
    "stores": 470
  },
  {
    "date": "2022-04-01",
    "profit": 34534,
    "stores": 380
  },
  {
    "date": "2022-05-01",
    "profit": 42001,
    "stores": 503
  }
]
